cakeutils/__init__.py
cakeutils/crc.py
cakeutils/cstruct.py
cakeutils/daemon.py
cakeutils/interceptor.py
cakeutils/log.py
cakeutils/mitm.py
cakeutils/netfilter.py
cakeutils/recvmsg.py
cakeutils/sidelog.py
cakeutils/strings.py
cakeutils-0.2.dist-info/METADATA
cakeutils-0.2.dist-info/WHEEL
cakeutils-0.2.dist-info/top_level.txt
cakeutils-0.2.dist-info/RECORD
