Metadata-Version: 2.1
Name: cakeutils
Version: 0.2
Summary: Cake utils: tools to make the cake
Home-page: http://www.secdev.org/projects/cakeutils/
Author: Philippe BIONDI
Author-email: phil@secdev.org
License: GPLv2
Platform: UNKNOWN
